tests/__init__.py
tests/test_addressable.py
tests/test_cupra.py
tests/test_elements.py
weconnect_cupra/__init__.py
weconnect_cupra/__version.py
weconnect_cupra/addressable.py
weconnect_cupra/errors.py
weconnect_cupra/fetch.py
weconnect_cupra/service.py
weconnect_cupra/util.py
weconnect_cupra/weconnect_cupra.py
weconnect_cupra/weconnect_errors.py
weconnect_cupra/api/__init__.py
weconnect_cupra/api/cupra/__init__.py
weconnect_cupra/api/cupra/api.py
weconnect_cupra/api/cupra/domain.py
weconnect_cupra/api/cupra/auth/__init__.py
weconnect_cupra/api/cupra/auth/my_cupra_session.py
weconnect_cupra/api/cupra/elements/__init__.py
weconnect_cupra/api/cupra/elements/access_status.py
weconnect_cupra/api/cupra/elements/battery_status.py
weconnect_cupra/api/cupra/elements/charging_settings.py
weconnect_cupra/api/cupra/elements/charging_station.py
weconnect_cupra/api/cupra/elements/charging_status.py
weconnect_cupra/api/cupra/elements/climatization_settings.py
weconnect_cupra/api/cupra/elements/climatization_status.py
weconnect_cupra/api/cupra/elements/connection_status.py
weconnect_cupra/api/cupra/elements/controls.py
weconnect_cupra/api/cupra/elements/engine_state.py
weconnect_cupra/api/cupra/elements/enums.py
weconnect_cupra/api/cupra/elements/error.py
weconnect_cupra/api/cupra/elements/generic_capability.py
weconnect_cupra/api/cupra/elements/generic_settings.py
weconnect_cupra/api/cupra/elements/odometer_measurement.py
weconnect_cupra/api/cupra/elements/parking_position.py
weconnect_cupra/api/cupra/elements/vehicle.py
weconnect_cupra/api/cupra/elements/helpers/__init__.py
weconnect_cupra/api/cupra/elements/helpers/request_tracker.py
weconnect_cupra/api/vw/__init__.py
weconnect_cupra/api/vw/api.py
weconnect_cupra/api/vw/domain.py
weconnect_cupra/api/vw/auth/__init__.py
weconnect_cupra/api/vw/auth/we_charge_session.py
weconnect_cupra/api/vw/auth/we_connect_session.py
weconnect_cupra/api/vw/elements/__init__.py
weconnect_cupra/api/vw/elements/access_status.py
weconnect_cupra_sren09-0.50.17.dist-info/licenses/LICENSE
weconnect_cupra_sren09-0.50.17.dist-info/METADATA
weconnect_cupra_sren09-0.50.17.dist-info/WHEEL
weconnect_cupra_sren09-0.50.17.dist-info/top_level.txt
weconnect_cupra_sren09-0.50.17.dist-info/RECORD
