Metadata-Version: 2.4
Name: weconnect-cupra-sren09
Version: 0.50.17
Summary: Python API for the Cupra Born online services
Home-page: https://github.com/daernsinstantfortress/WeConnect-Cupra-python
Author: Till Steinbach / Alan Gibson / Stuart Hall
License: MIT
Project-URL: Funding, https://github.com/sponsors/tillsteinbach
Project-URL: Source, https://github.com/daernsinstantfortress/WeConnect-Cupra-python
Project-URL: Bug Tracker, https://github.com/daernsinstantfortress/WeConnect-Cupra-python/issues
Keywords: weconnect_cupra,weconnect,we connect,carnet,car net,volkswagen,vw,telemetry,cupra
Classifier: Development Status :: 3 - Alpha
Classifier: License :: OSI Approved :: MIT License
Classifier: Intended Audience :: Developers
Classifier: Programming Language :: Python :: 3.7
Classifier: Programming Language :: Python :: 3.8
Classifier: Programming Language :: Python :: 3.9
Classifier: Programming Language :: Python :: 3.10
Classifier: Programming Language :: Python :: 3.11
Classifier: Topic :: Software Development :: Libraries
Requires-Python: >=3.7
License-File: LICENSE
Requires-Dist: requests>=2.28.0
Requires-Dist: oauthlib~=3.2.0
Provides-Extra: images
Requires-Dist: pillow~=10.0.0; extra == "images"
Requires-Dist: ascii_magic~=2.1.1; extra == "images"
Dynamic: author
Dynamic: classifier
Dynamic: description
Dynamic: description-content-type
Dynamic: home-page
Dynamic: keywords
Dynamic: license
Dynamic: license-file
Dynamic: project-url
Dynamic: provides-extra
Dynamic: requires-dist
Dynamic: requires-python
Dynamic: summary
